koala/__init__.py
koala/classes.py
koala/alignment/__init__.py
koala/alignment/alignment_square.gds
koala-1.0.3.dist-info/LICENSE
koala-1.0.3.dist-info/METADATA
koala-1.0.3.dist-info/WHEEL
koala-1.0.3.dist-info/top_level.txt
koala-1.0.3.dist-info/RECORD
