Metadata-Version: 2.1
Name: koala
Version: 1.0.3
Summary: KlayOut mAsk Layout Automation (KOALA) provides a user-friendly, easy-to-use interface for (photo)mask design.
Author-email: Imke Krauhausen <i.krauhausen@tue.nl>, Charles-Théophile Coen <c.t.coen@tue.nl>, Simone Spolaor <s.spolaor@tue.nl>
Project-URL: repository, https://gitlab.tue.nl/20210538/klayout-mask-layout-automation
Keywords: mask layout,photolithography
Classifier: Programming Language :: Python :: 3
Classifier: License :: OSI Approved :: GNU General Public License v3 (GPLv3)
Classifier: Operating System :: OS Independent
Requires-Python: >=3.7
License-File: LICENSE
Requires-Dist: klayout
Requires-Dist: numpy
